docker_develop/__init__.py
docker_develop/__main__.py
docker_develop-1.1.3.dist-info/LICENSE
docker_develop-1.1.3.dist-info/METADATA
docker_develop-1.1.3.dist-info/WHEEL
docker_develop-1.1.3.dist-info/entry_points.txt
docker_develop-1.1.3.dist-info/top_level.txt
docker_develop-1.1.3.dist-info/RECORD
