Metadata-Version: 2.1
Name: docker-develop
Version: 1.1.3
Summary: Distirbuted docker-compose configurations for software development.
Author: Michał Góra
Author-email: Tomasz Bogdał <tomek@cledar.com>
Maintainer-email: Tomasz Bogdał <tomek@cledar.com>
License: MPL-2
Project-URL: homepage, https://github.com/cledar/docker-develop
Project-URL: repository, https://github.com/cledar/docker-develop
Project-URL: documentation, https://github.com/cledar/docker-develop/README.md
Keywords: docker,docker-compose,development,distributed
Classifier: Intended Audience :: Developers
Classifier: Development Status :: 5 - Production/Stable
Classifier: License :: OSI Approved :: Mozilla Public License 2.0 (MPL 2.0)
Classifier: Operating System :: POSIX :: Linux
Classifier: Operating System :: MacOS
Classifier: Operating System :: MacOS :: MacOS X
Classifier: Programming Language :: Python :: 3
License-File: LICENSE
Requires-Dist: pyyaml
